{
    "err_msg": {
        "text": "hadoop. hbase. security. AccessDeniedException: Insufficient permissions",
        "lines": ["title"],
        "weight": [1]
    },
    "scene": [
        {
            "text": "hbase查找",
            "lines": [4],
            "weight": [1]
        },
        {
            "text": "hive查表",
            "lines": [4],
            "weight": [1]
        }
    ],
    "solve": {
        "text": "在进行hbase查询前，再一次登录hbase的用户\n\nUserGroupInformation.loginUserFromKeytab(principal, keytab);",
        "lines": [13, 15],
        "weight": [1, 0.5]
    },
    "solve_secs": [
        [9, 17]
    ]
}