{
    "err_msg": {
        "text": "RuntimeError: maximum recursion depth exceeded",
        "lines": ["title"],
        "weight": [1]
    },
    "scene": {
        "text": "python递归深度",
        "lines": ["title"],
        "weight": [1]
    },
    "solve": [
        {
            "text": "增加系统的递归调用的次数：\n\nimport sys\n\nsys.setrecursionlimit(n)  n为你想要的递归上限",
            "lines": [5, 7, 9],
            "weight": [1, 1, 1]       
        },
        {
            "text": "优化代码，减少递归的次数",
            "lines": [11],
            "weight": [1]
        }
    ],
    "solve_secs": [
        [3, "eof"]
    ]
}