{
    "err_msg": {
        "text": "OSError: Initializing from file failed",
        "lines": [20],
        "weight": [1]
    },
    "scene": [
        {
            "text": "python  使用read_csv读取 CSV 文件",
            "lines": ["title"],
            "weight": [1]
        },
        {
            "text": "读取csv文件",
            "lines": [1],
            "weight": [1]
        }
    ],
    "solve": {
        "text": "df = pd.read_csv('c:/Users/NUC/Desktop/成绩.csv', engine='python' )\n加上 engine = 'python'",
        "lines": [24, 25],
        "weight": [0.5, 1]
    }
}